{
  "sections": {
    "main-page": {
      "type": "main-page",
      "disabled": true,
      "settings": {
        "heading_size": "title-xl tracking-heading",
        "heading_tag": "h1",
        "text_size": "text-base",
        "padding_top": 72,
        "padding_bottom": 120,
        "divider": false,
        "narrow": true,
        "rounded": false
      }
    },
    "countdown_timer_7hMhKU": {
      "type": "countdown-timer",
      "blocks": {
        "heading_jnHJfW": {
          "type": "heading",
          "settings": {
            "heading": "",
            "heading_size": "title-sm",
            "heading_tag": "h2",
            "highlighted_text": "none",
            "highlighted_scribble": "circle"
          }
        },
        "timer_XzcYE4": {
          "type": "timer",
          "settings": {
            "year": "2024",
            "month": "04",
            "day": "23",
            "hour": "00",
            "minute": "00",
            "text_font": "heading",
            "text_size": "title-sm",
            "message": ""
          }
        }
      },
      "block_order": [
        "heading_jnHJfW",
        "timer_XzcYE4"
      ],
      "disabled": true,
      "settings": {
        "transparent_header": false,
        "image": "shopify:\/\/shop_images\/PC_e58c48f0-f537-4f70-8361-0d5a071d809a.jpg",
        "image_height": "adapt",
        "content_width": "small",
        "content_position": "md:items-start md:justify-end",
        "text_alignment": "center",
        "image_mobile": "shopify:\/\/shop_images\/M_46e3efe6-70d7-4ef3-8a45-c160872d847a.jpg",
        "image_height_mobile": "adapt",
        "content_position_mobile": "items-end justify-center",
        "text_alignment_mobile": "center",
        "color_text": "#100f0f",
        "color_highlight": "#e0a580",
        "gradient_highlight": "",
        "color_button_text": "#171717",
        "color_button_background": "#ffffff",
        "color_button_gradient": "",
        "color_overlay": "#171717",
        "overlay_opacity": 0,
        "padding_top": 0,
        "padding_bottom": 0,
        "divider": false,
        "full_width": true,
        "rounded": false,
        "enable_parallax": false,
        "parallax_direction": "vertical"
      }
    },
    "air10_banner_k6tjDe": {
      "type": "air10-banner",
      "settings": {
        "title": "Air10",
        "subheading": "シリーズ",
        "des": "<p>効果と快適さを両立<\/p><p>Ulike史上最高パワー<\/p>",
        "button_txt": "早割セール限定10%OFF→",
        "link_url": "shopify:\/\/products\/air10-ipl-hair-removal",
        "image": "shopify:\/\/shop_images\/pc_0d810908-efc9-40ae-8f04-ccbf9fbd9728.jpg",
        "image_mobile": "shopify:\/\/shop_images\/M_cb43a00d-b151-47de-a36b-c8a555c75189.jpg",
        "text_color": "rgba(0,0,0,0)",
        "background": "rgba(0,0,0,0)"
      }
    },
    "rich_text_9QNjGY": {
      "type": "rich-text",
      "blocks": {
        "text_YMCDpW": {
          "type": "text",
          "settings": {
            "text": "<p>電動歯ブラシは商品と別送となります。（商品到着から7日～14日後）<\/p>",
            "text_size": "subtext-sm",
            "text_max_size": 32,
            "text_font": "body",
            "secondary_color": true,
            "highlighted_text": "none",
            "highlighted_scribble": "circle"
          }
        }
      },
      "block_order": [
        "text_YMCDpW"
      ],
      "disabled": true,
      "settings": {
        "text_alignment": "center",
        "text_alignment_mobile": "center",
        "heading": "",
        "heading_size": "title-sm",
        "heading_alignment": "text-center md:items-center",
        "heading_tag": "h2",
        "subheading": "",
        "description": "",
        "button_label": "",
        "button_link": "",
        "highlighted_text": "none",
        "highlighted_scribble": "circle",
        "color_text": "",
        "color_background": "#fae6ea",
        "gradient_background": "",
        "color_highlight": "",
        "gradient_highlight": "",
        "color_button_text": "",
        "color_button_background": "",
        "color_button_gradient": "",
        "padding_top": 0,
        "padding_bottom": 12,
        "divider": false,
        "narrow": true,
        "rounded": false
      }
    },
    "rich_text_KqEygY": {
      "type": "rich-text",
      "blocks": {
        "heading_6irhy4": {
          "type": "heading",
          "settings": {
            "heading": "家庭用光美容器の販売台数<em>世界NO.1*<\/em>",
            "heading_size": "title-sm",
            "heading_tag": "h2",
            "highlighted_text": "scribble",
            "highlighted_scribble": "squiggle-underline"
          }
        },
        "text_DW4KcV": {
          "type": "text",
          "settings": {
            "text": "<p>Ulikeは、サロングレードのムダ毛ケアを、誰もがご自宅で手軽に楽しめるようにすることを目指しています。<\/p>",
            "text_size": "subtext-md",
            "text_max_size": 32,
            "text_font": "body",
            "secondary_color": false,
            "highlighted_text": "none",
            "highlighted_scribble": "circle"
          }
        },
        "liquid_HR39VT": {
          "type": "liquid",
          "disabled": true,
          "settings": {
            "liquid": "<p style=\"\n    font-weight: bold;\n    font-size: 16px;\n    margin-bottom: 0px;\n\">仕事で忙しい毎日にこそ、美しさと癒しの時間を。<\/p>\n<p style=\"\n    margin: 0px;\n\"><\/p>\n<p style=\"\n    font-weight: bold;\n    font-size: 16px;\n    margin: 2px;\n\">Ulikeアンバサダー山本舞香も愛用中の光美容器で、自宅でサロン級のケアを体験しませんか？\n<\/p>\n<p style=\"\n    font-weight: bold;\n    font-size: 16px;\n    margin: 2px;\n\">新しい生活を美しく迎えましょう。<\/p>"
          }
        },
        "text_38UFjm": {
          "type": "text",
          "disabled": true,
          "settings": {
            "text": "<p>仕事で忙しい毎日にこそ、美しさと癒しの時間を。<br\/>Ulikeアンバサダー山本舞香も愛用中の光美容器で、自宅でサロン級のケアを体験しませんか？<br\/>新しい生活を美しく迎えましょう。<\/p>",
            "text_size": "subtext-sm",
            "text_max_size": 32,
            "text_font": "body",
            "secondary_color": false,
            "highlighted_text": "none",
            "highlighted_scribble": "circle"
          }
        }
      },
      "block_order": [
        "heading_6irhy4",
        "text_DW4KcV",
        "liquid_HR39VT",
        "text_38UFjm"
      ],
      "settings": {
        "text_alignment": "center",
        "text_alignment_mobile": "center",
        "heading": "",
        "heading_size": "title-md",
        "heading_alignment": "text-left md:items-end md:flex-row",
        "heading_tag": "h2",
        "subheading": "",
        "description": "",
        "button_label": "",
        "button_link": "",
        "highlighted_text": "none",
        "highlighted_scribble": "circle",
        "color_text": "",
        "color_background": "#ffffff",
        "gradient_background": "",
        "color_highlight": "",
        "gradient_highlight": "",
        "color_button_text": "",
        "color_button_background": "",
        "color_button_gradient": "",
        "padding_top": 48,
        "padding_bottom": 48,
        "divider": false,
        "narrow": true,
        "rounded": false
      }
    },
    "images_with_text_VM9xpj": {
      "type": "images-with-text",
      "blocks": {
        "heading_yFn8me": {
          "type": "heading",
          "settings": {
            "heading": "世界17ヶ国で500万人以上が選ぶ信頼と品質！",
            "heading_size": "title-sm",
            "heading_tag": "h2",
            "highlighted_text": "none",
            "highlighted_scribble": "circle"
          }
        },
        "text_KAe7P8": {
          "type": "text",
          "settings": {
            "text": "<p>Ulikeは、サロングレードのムダ毛ケアを、誰もがご自宅で手軽に楽しめるようにすることを目指しています。<br\/><\/p>",
            "text_size": "subtext-xl",
            "text_max_size": 32,
            "text_font": "body",
            "secondary_color": false,
            "highlighted_text": "none",
            "highlighted_scribble": "circle"
          }
        },
        "text_HTNXqD": {
          "type": "text",
          "settings": {
            "text": "<p>*ユーロモニターインターナショナル調べ；2022年世界の家庭用光美容器の小売販売台数から測定；2023年12月に実施された調査に基づく；家庭用光美容器とは、IPLやレーザーといった光エネルギーを利用して無駄毛を処理する家庭用機器を指す。<\/p>",
            "text_size": "subtext-custom",
            "text_max_size": 12,
            "text_font": "body",
            "secondary_color": true,
            "highlighted_text": "none",
            "highlighted_scribble": "circle"
          }
        }
      },
      "block_order": [
        "heading_yFn8me",
        "text_KAe7P8",
        "text_HTNXqD"
      ],
      "disabled": true,
      "settings": {
        "image": "shopify:\/\/shop_images\/2_7.jpg",
        "image_ratio": "square",
        "image_width": "medium",
        "layout": "image_first",
        "text_alignment": "left",
        "text_alignment_mobile": "center",
        "color_text": "",
        "color_background": "#ffffff",
        "gradient_background": "",
        "color_highlight": "",
        "gradient_highlight": "",
        "color_button_text": "",
        "color_button_background": "",
        "color_button_gradient": "",
        "padding_top": 0,
        "padding_bottom": 20,
        "divider": false,
        "full_width": false,
        "rounded": false,
        "enable_parallax": true
      }
    },
    "image_with_text_mRRfzk": {
      "type": "image-with-text",
      "blocks": {
        "heading_Qrwmrf": {
          "type": "heading",
          "settings": {
            "heading": "Ulike<strong> <\/strong><em>Air 3<\/em> IPL 光美容器",
            "heading_size": "title-sm",
            "heading_tag": "h2",
            "highlighted_text": "scribble",
            "highlighted_scribble": "circle"
          }
        },
        "text_rexeCM": {
          "type": "text",
          "settings": {
            "text": "<ul><li><strong>6回でハッキリ減毛効果を実感<\/strong><\/li><li><strong>30分間ひんやり感が持続<\/strong><\/li><li><strong>VIO対応 - 完璧なプライバシー<\/strong><\/li><li><strong>約12分でおうちで全身時短ケア<\/strong><\/li><\/ul>",
            "text_size": "subtext-custom",
            "text_max_size": 18,
            "text_font": "body",
            "secondary_color": false,
            "highlighted_text": "none",
            "highlighted_scribble": "circle"
          }
        },
        "liquid_dK44iU": {
          "type": "liquid",
          "settings": {
            "liquid": "<p>\n  <font size=\"5\" color=\"#666666\">\n    <del>￥48,000<\/del> <span style=\"font-size: 12px;\">税込<\/span> → <span style=\"font-size: 26px; font-weight: 500; color: #E0004D;\">￥33,600<\/span><span style=\"font-size: 12px;\">税込<\/span>\n  <\/font>\n<\/p>\n<p\/>"
          }
        },
        "button_b7qkje": {
          "type": "button",
          "settings": {
            "button_label": "今すぐ購入",
            "button_link": "shopify:\/\/products\/air3-hair-removal",
            "button_size": "sm",
            "button_secondary_style": true
          }
        }
      },
      "block_order": [
        "heading_Qrwmrf",
        "text_rexeCM",
        "liquid_dK44iU",
        "button_b7qkje"
      ],
      "disabled": true,
      "settings": {
        "image": "shopify:\/\/shop_images\/Air3_542810a1-f571-460b-a50b-dbf468e31a7e.jpg",
        "image_height": "adapt",
        "image_width": "medium",
        "layout": "image_first",
        "text_alignment": "left",
        "image_height_mobile": "adapt",
        "text_alignment_mobile": "left",
        "color_text": "",
        "color_background": "#ffffff",
        "gradient_background": "",
        "color_background_2": "",
        "gradient_background_2": "",
        "color_highlight": "",
        "gradient_highlight": "",
        "color_button_text": "",
        "color_button_background": "",
        "color_button_gradient": "",
        "padding_top": 0,
        "padding_bottom": 0,
        "divider": false,
        "full_width": false,
        "rounded": false,
        "enable_parallax": false,
        "parallax_direction": "vertical"
      }
    },
    "image_with_text_ew8B4b": {
      "type": "image-with-text",
      "blocks": {
        "heading_8WpVVw": {
          "type": "heading",
          "settings": {
            "heading": "Ulike<strong> <\/strong><em>Men<\/em> IPL 光美容器",
            "heading_size": "title-sm",
            "heading_tag": "h2",
            "highlighted_text": "scribble",
            "highlighted_scribble": "circle"
          }
        },
        "text_xW3rGi": {
          "type": "text",
          "settings": {
            "text": "<ul><li><strong>男性の太く硬い毛に特化25J超ハイパワー<\/strong><\/li><li><strong>ダブルランプで一週間の使用で効果を実感<\/strong><\/li><li><strong>サファイア冷感技術でハイパワーなのに痛みレス<\/strong><\/li><li><strong>自動高速フラッシュ機能で時短ケアを実現<\/strong><\/li><li><strong>肌色感知機能で最適な照射パワーを、安全安心<\/strong><\/li><\/ul>",
            "text_size": "subtext-custom",
            "text_max_size": 18,
            "text_font": "body",
            "secondary_color": false,
            "highlighted_text": "none",
            "highlighted_scribble": "circle"
          }
        },
        "liquid_U6XNkB": {
          "type": "liquid",
          "settings": {
            "liquid": "<p>\n  <font size=\"5\" color=\"#666666\">\n    <del>￥71,800<\/del> <span style=\"font-size: 12px;\">税込<\/span> → <span style=\"font-size: 26px; font-weight: 500; color: #E0004D;\">￥61,030<\/span><span style=\"font-size: 12px;\">税込<\/span>\n  <\/font>\n<\/p>\n<p\/>"
          }
        },
        "button_3jJxHB": {
          "type": "button",
          "settings": {
            "button_label": "今すぐ購入",
            "button_link": "shopify:\/\/products\/ulike-men-ipl-hair-removal",
            "button_size": "sm",
            "button_secondary_style": true
          }
        }
      },
      "block_order": [
        "heading_8WpVVw",
        "text_xW3rGi",
        "liquid_U6XNkB",
        "button_3jJxHB"
      ],
      "settings": {
        "image": "shopify:\/\/shop_images\/UIM_20.png",
        "image_height": "adapt",
        "image_width": "medium",
        "layout": "text_first",
        "text_alignment": "left",
        "image_height_mobile": "adapt",
        "text_alignment_mobile": "left",
        "color_text": "",
        "color_background": "#ffffff",
        "gradient_background": "",
        "color_background_2": "",
        "gradient_background_2": "",
        "color_highlight": "",
        "gradient_highlight": "",
        "color_button_text": "",
        "color_button_background": "",
        "color_button_gradient": "",
        "padding_top": 0,
        "padding_bottom": 0,
        "divider": false,
        "full_width": false,
        "rounded": false,
        "enable_parallax": false,
        "parallax_direction": "vertical"
      }
    },
    "image_with_text_DnWprU": {
      "type": "image-with-text",
      "blocks": {
        "heading_PJAHqc": {
          "type": "heading",
          "settings": {
            "heading": "Ulike <em>Air 2<\/em> IPL光美容器 (メンズ)",
            "heading_size": "title-sm",
            "heading_tag": "h2",
            "highlighted_text": "scribble",
            "highlighted_scribble": "circle"
          }
        },
        "text_ziJEaN": {
          "type": "text",
          "settings": {
            "text": "<ul><li><strong>男性専用のハイパワー<\/strong><\/li><li><strong>超冷感！カートリッジ不要<\/strong><\/li><li><strong>最高レベルでも1,000,000発<\/strong><\/li><li><strong>VIOまで対応の全身ケア<\/strong><br\/><br\/><\/li><\/ul>",
            "text_size": "subtext-custom",
            "text_max_size": 18,
            "text_font": "body",
            "secondary_color": false,
            "highlighted_text": "none",
            "highlighted_scribble": "circle"
          }
        },
        "liquid_AbmdzG": {
          "type": "liquid",
          "settings": {
            "liquid": "<p>\n  <font size=\"5\" color=\"#666666\">\n    <del>￥58,000<\/del> <span style=\"font-size: 12px;\">税込<\/span> → <span style=\"font-size: 26px; font-weight: 500; color: #E0004D;\">￥49,300<\/span><span style=\"font-size: 12px;\">税込<\/span>\n  <\/font>\n<\/p>\n<p\/>"
          }
        },
        "button_H33iFD": {
          "type": "button",
          "settings": {
            "button_label": "今すぐ購入",
            "button_link": "shopify:\/\/products\/men-air2",
            "button_size": "sm",
            "button_secondary_style": true
          }
        }
      },
      "block_order": [
        "heading_PJAHqc",
        "text_ziJEaN",
        "liquid_AbmdzG",
        "button_H33iFD"
      ],
      "settings": {
        "image": "shopify:\/\/shop_images\/Air2_bb7e259a-ac43-4624-ac24-20004ed9c532.jpg",
        "image_height": "adapt",
        "image_width": "medium",
        "layout": "image_first",
        "text_alignment": "left",
        "image_height_mobile": "adapt",
        "text_alignment_mobile": "left",
        "color_text": "",
        "color_background": "#ffffff",
        "gradient_background": "",
        "color_background_2": "",
        "gradient_background_2": "",
        "color_highlight": "",
        "gradient_highlight": "",
        "color_button_text": "",
        "color_button_background": "",
        "color_button_gradient": "",
        "padding_top": 0,
        "padding_bottom": 0,
        "divider": false,
        "full_width": false,
        "rounded": false,
        "enable_parallax": false,
        "parallax_direction": "vertical"
      }
    },
    "image_with_text_Tn8xy6": {
      "type": "image-with-text",
      "blocks": {
        "heading_hHNLyH": {
          "type": "heading",
          "settings": {
            "heading": "Ulike <em>Air Pro <\/em>IPL光美容器",
            "heading_size": "title-sm",
            "heading_tag": "h2",
            "highlighted_text": "scribble",
            "highlighted_scribble": "circle"
          }
        },
        "text_rWgmBA": {
          "type": "text",
          "settings": {
            "text": "<ul><li><strong>4週間で効果を実感<\/strong><\/li><li><strong>サファイア冷感技術搭載<\/strong><\/li><li><strong>サロン級の高出力で痛みレス<\/strong><\/li><li><strong>全身一回あたりにたった15円<\/strong><\/li><\/ul>",
            "text_size": "subtext-custom",
            "text_max_size": 18,
            "text_font": "body",
            "secondary_color": false,
            "highlighted_text": "none",
            "highlighted_scribble": "circle"
          }
        },
        "liquid_33Yay6": {
          "type": "liquid",
          "settings": {
            "liquid": "<p>\n  <font size=\"5\" color=\"#666666\">\n    <del>￥39,000<\/del> <span style=\"font-size: 12px;\">税込<\/span> → <span style=\"font-size: 26px; font-weight: 500; color: #E0004D;\">￥29,250<\/span><span style=\"font-size: 12px;\">税込<\/span>\n  <\/font>\n<\/p>\n<p\/>"
          }
        },
        "button_miPX3R": {
          "type": "button",
          "settings": {
            "button_label": "今すぐ購入",
            "button_link": "shopify:\/\/products\/ulike-air-z",
            "button_size": "sm",
            "button_secondary_style": true
          }
        }
      },
      "block_order": [
        "heading_hHNLyH",
        "text_rWgmBA",
        "liquid_33Yay6",
        "button_miPX3R"
      ],
      "settings": {
        "image": "shopify:\/\/shop_images\/ae7bedbf403e34173bd58b1e3b740a66.png",
        "image_height": "adapt",
        "image_width": "medium",
        "layout": "text_first",
        "text_alignment": "left",
        "image_height_mobile": "adapt",
        "text_alignment_mobile": "left",
        "color_text": "",
        "color_background": "#ffffff",
        "gradient_background": "",
        "color_background_2": "",
        "gradient_background_2": "",
        "color_highlight": "",
        "gradient_highlight": "",
        "color_button_text": "",
        "color_button_background": "rgba(0,0,0,0)",
        "color_button_gradient": "",
        "padding_top": 0,
        "padding_bottom": 0,
        "divider": false,
        "full_width": false,
        "rounded": false,
        "enable_parallax": false,
        "parallax_direction": "vertical"
      }
    },
    "preheat_slide_diy_BbbmNt": {
      "type": "preheat-slide-diy",
      "blocks": {
        "item_gy3Nk8": {
          "type": "item",
          "settings": {
            "image1": "shopify:\/\/shop_images\/Mask_group-6_72f44660-9557-4011-ad2f-285d48ea0ece.jpg",
            "image2": "shopify:\/\/shop_images\/Mask_group-7_37f633bf-b2d3-422c-851f-e23a8bdf799e.jpg",
            "image": "shopify:\/\/shop_images\/Group_Button-3.jpg",
            "text": "VIO"
          }
        },
        "item_Vqe6xh": {
          "type": "item",
          "settings": {
            "image1": "shopify:\/\/shop_images\/Mask_group_096204be-bc88-407c-973f-b108f9afb950.jpg",
            "image2": "shopify:\/\/shop_images\/Mask_group-1_96af4f09-9652-4097-8c00-cfda126e1a05.jpg",
            "image": "shopify:\/\/shop_images\/Group_Button.jpg",
            "text": "脇"
          }
        },
        "item_MprdJK": {
          "type": "item",
          "settings": {
            "image1": "shopify:\/\/shop_images\/Mask_group-2_698aeddc-b51f-4df7-b9c7-25eb450621a3.jpg",
            "image2": "shopify:\/\/shop_images\/Mask_group-3_c6124966-6df9-4ecf-9d9e-b9a96d372cb1.jpg",
            "image": "shopify:\/\/shop_images\/Group_Button-1.jpg",
            "text": "脚"
          }
        },
        "item_4jyNPw": {
          "type": "item",
          "settings": {
            "image1": "shopify:\/\/shop_images\/Mask_group-4_7b4b2b55-2979-41a8-b110-82e7e275ad76.jpg",
            "image2": "shopify:\/\/shop_images\/Mask_group-5_1a5e1a93-8017-408a-a000-ae88609b3ffa.jpg",
            "image": "shopify:\/\/shop_images\/Group_Button-2.jpg",
            "text": "腕"
          }
        }
      },
      "block_order": [
        "item_gy3Nk8",
        "item_Vqe6xh",
        "item_MprdJK",
        "item_4jyNPw"
      ],
      "settings": {
        "text": "<p>毛髪密度が1週間で77.4％減少、<\/p><p>2週間で92.47％減少*<\/p>",
        "text1": "",
        "text2": "Before",
        "text3": "After",
        "text4": "*国際認証機関SGSにて、19～54歳の女性32名を対象としたAir10の使用で前腕の試験結果です。"
      }
    },
    "featured_collection_FMUB6U": {
      "type": "featured-collection",
      "settings": {
        "collection": "",
        "products": [
          "air10-ipl-hair-removal",
          "air3-hair-removal",
          "ulike-air-z",
          "ulike-air-a"
        ],
        "product_limit": 6,
        "columns": 4,
        "carousel_on_desktop": true,
        "show_view_all": false,
        "columns_mobile": "1",
        "swipe_on_mobile": true,
        "heading": "人気製品",
        "heading_size": "title-sm",
        "heading_alignment": "text-center md:items-center",
        "heading_tag": "h2",
        "subheading": "",
        "description": "",
        "highlighted_text": "none",
        "highlighted_scribble": "circle",
        "color_text": "",
        "color_background": "",
        "gradient_background": "",
        "color_highlight": "",
        "gradient_highlight": "",
        "color_button_text": "",
        "color_button_background": "",
        "color_button_gradient": "",
        "padding_top": 72,
        "padding_bottom": 72,
        "divider": false,
        "full_width": false,
        "rounded": false
      }
    },
    "image_with_text_NpDc6j": {
      "type": "image-with-text",
      "blocks": {
        "heading_n9QkUn": {
          "type": "heading",
          "settings": {
            "heading": "Ulike<strong> <\/strong><em>Air <\/em> IPL 光美容器",
            "heading_size": "title-sm",
            "heading_tag": "h2",
            "highlighted_text": "scribble",
            "highlighted_scribble": "circle"
          }
        },
        "text_BmKBWx": {
          "type": "text",
          "settings": {
            "text": "<ul><li><strong>おうちで極上なムダ毛ケアを体感<\/strong><\/li><li><strong>サファイア冷感技術で痛みレス<\/strong><\/li><li><strong>VIO対応 - 完璧なプライバシー<\/strong><\/li><li><strong>4週間で驚きな変化を感じよう<\/strong><\/li><\/ul>",
            "text_size": "subtext-custom",
            "text_max_size": 18,
            "text_font": "body",
            "secondary_color": false,
            "highlighted_text": "none",
            "highlighted_scribble": "circle"
          }
        },
        "liquid_L8Ai4G": {
          "type": "liquid",
          "settings": {
            "liquid": "<p>\n  <font size=\"5\" color=\"#666666\">\n    <del>￥33,000<\/del> <span style=\"font-size: 12px;\">税込<\/span> → <span style=\"font-size: 26px; font-weight: 500; color: #E0004D;\">￥23,100<\/span><span style=\"font-size: 12px;\">税込<\/span>\n  <\/font>\n<\/p>\n<p\/>"
          }
        },
        "button_RJNHB9": {
          "type": "button",
          "settings": {
            "button_label": "今すぐ購入",
            "button_link": "shopify:\/\/products\/ulike-air-a",
            "button_size": "sm",
            "button_secondary_style": true
          }
        }
      },
      "block_order": [
        "heading_n9QkUn",
        "text_BmKBWx",
        "liquid_L8Ai4G",
        "button_RJNHB9"
      ],
      "disabled": true,
      "settings": {
        "image": "shopify:\/\/shop_images\/Air_9cfa5645-ea7b-4c97-9ea9-15ce13c9dd5d.jpg",
        "image_height": "adapt",
        "image_width": "medium",
        "layout": "text_first",
        "text_alignment": "left",
        "image_height_mobile": "adapt",
        "text_alignment_mobile": "left",
        "color_text": "",
        "color_background": "#ffffff",
        "gradient_background": "",
        "color_background_2": "",
        "gradient_background_2": "",
        "color_highlight": "",
        "gradient_highlight": "",
        "color_button_text": "",
        "color_button_background": "",
        "color_button_gradient": "",
        "padding_top": 0,
        "padding_bottom": 0,
        "divider": false,
        "full_width": false,
        "rounded": false,
        "enable_parallax": false,
        "parallax_direction": "vertical"
      }
    },
    "rich_text_Yp4nKi": {
      "type": "rich-text",
      "blocks": {
        "heading_J6XeQE": {
          "type": "heading",
          "settings": {
            "heading": "Ulike Men IPL光美容器",
            "heading_size": "title-sm",
            "heading_tag": "h2",
            "highlighted_text": "none",
            "highlighted_scribble": "circle"
          }
        },
        "liquid_mKgqBB": {
          "type": "liquid",
          "settings": {
            "liquid": "<p style=\"\n    font-weight: bold;\n    font-size: 16px;\n    margin-bottom: 0px;\n\">史上最強パワー*、男性専用の最新型、Ulike Menはついに上陸！<\/p>\n<p style=\"\n    margin: 0px;\n\"><\/p>\n<p style=\"\n    font-size: 12px;\n    margin: 4px;\n\">*当社従来品比較。<\/p>"
          }
        },
        "liquid_QrwURr": {
          "type": "liquid",
          "settings": {
            "liquid": "<p>\n  <span style=\"font-size: 26px; font-weight: 500; color: #E0004D;\">￥71,800<\/span><span style=\"font-size: 12px;\">税込<\/span>\n  <\/font>\n<\/p>\n<p\/>"
          }
        },
        "button_63Wbrd": {
          "type": "button",
          "settings": {
            "button_label": "今すぐ購入",
            "button_link": "shopify:\/\/products\/ulike-men-ipl-hair-removal",
            "button_size": "sm",
            "button_secondary_style": true
          }
        }
      },
      "block_order": [
        "heading_J6XeQE",
        "liquid_mKgqBB",
        "liquid_QrwURr",
        "button_63Wbrd"
      ],
      "disabled": true,
      "settings": {
        "text_alignment": "center",
        "text_alignment_mobile": "center",
        "heading": "",
        "heading_size": "title-md",
        "heading_alignment": "text-left md:items-end md:flex-row",
        "heading_tag": "h2",
        "subheading": "",
        "description": "",
        "button_label": "",
        "button_link": "",
        "highlighted_text": "none",
        "highlighted_scribble": "circle",
        "color_text": "",
        "color_background": "#fae6ea",
        "gradient_background": "",
        "color_highlight": "",
        "gradient_highlight": "",
        "color_button_text": "",
        "color_button_background": "",
        "color_button_gradient": "",
        "padding_top": 32,
        "padding_bottom": 32,
        "divider": false,
        "narrow": true,
        "rounded": false
      }
    },
    "image_with_text_overlay_ACKQTF": {
      "type": "image-with-text-overlay",
      "disabled": true,
      "settings": {
        "transparent_header": false,
        "image": "shopify:\/\/shop_images\/20240315-140851.jpg",
        "image_height": "adapt",
        "content_width": "small",
        "content_position": "md:items-end md:justify-start",
        "text_alignment": "left",
        "image_mobile": "shopify:\/\/shop_images\/6_e5790f2d-f08d-4fe2-a2f1-d3f80b5fb637.jpg",
        "image_height_mobile": "adapt",
        "content_position_mobile": "items-end justify-start",
        "text_alignment_mobile": "left",
        "color_text": "#ffffff",
        "color_highlight": "#e0a580",
        "gradient_highlight": "",
        "color_button_text": "#171717",
        "color_button_background": "#ffffff",
        "color_button_gradient": "",
        "color_overlay": "#fff1f2",
        "overlay_opacity": 70,
        "padding_top": 0,
        "padding_bottom": 0,
        "divider": false,
        "full_width": true,
        "rounded": false,
        "enable_parallax": false,
        "parallax_direction": "vertical"
      }
    },
    "rich_text_Kp8ert": {
      "type": "rich-text",
      "blocks": {
        "heading_WeQUMb": {
          "type": "heading",
          "settings": {
            "heading": "おうちで、快適なムダ毛ケアを実現",
            "heading_size": "title-sm",
            "heading_tag": "h2",
            "highlighted_text": "none",
            "highlighted_scribble": "circle"
          }
        },
        "text_wttaPN": {
          "type": "text",
          "settings": {
            "text": "<p>これ一台で、顔からVIOまで全身対応。Ulike Airシリーズでストレスフリーのツルスベ肌へ<\/p>",
            "text_size": "subtext-md",
            "text_max_size": 32,
            "text_font": "body",
            "secondary_color": false,
            "highlighted_text": "none",
            "highlighted_scribble": "circle"
          }
        }
      },
      "block_order": [
        "heading_WeQUMb",
        "text_wttaPN"
      ],
      "disabled": true,
      "settings": {
        "text_alignment": "center",
        "text_alignment_mobile": "center",
        "heading": "",
        "heading_size": "title-md",
        "heading_alignment": "text-center md:items-center",
        "heading_tag": "h2",
        "subheading": "",
        "description": "",
        "button_label": "",
        "button_link": "",
        "highlighted_text": "none",
        "highlighted_scribble": "circle",
        "color_text": "",
        "color_background": "#ffffff",
        "gradient_background": "",
        "color_highlight": "",
        "gradient_highlight": "",
        "color_button_text": "",
        "color_button_background": "",
        "color_button_gradient": "",
        "padding_top": 56,
        "padding_bottom": 56,
        "divider": false,
        "narrow": true,
        "rounded": false
      }
    },
    "video_XX9qmL": {
      "type": "video",
      "disabled": true,
      "settings": {
        "transparent_header": false,
        "video": "shopify:\/\/files\/videos\/Air Pro product video - product tab 2.mp4",
        "video_url": "https:\/\/www.youtube.com\/watch?v=_9VUPq3SxOc",
        "description": "脱毛, 家庭用光美容器, 家庭用脱毛器, ムダ毛ケア, 脱毛メンズ",
        "enable_video_autoplay": true,
        "enable_video_looping": true,
        "image_height": "600px",
        "video_url_mobile": "",
        "image_height_mobile": "auto",
        "padding_top": 0,
        "padding_bottom": 56,
        "divider": false,
        "full_width": true,
        "rounded": false
      }
    },
    "rich_text_ixrKrJ": {
      "type": "rich-text",
      "blocks": {
        "heading_TLEnRH": {
          "type": "heading",
          "settings": {
            "heading": "Ulike IPL家庭用光美容器",
            "heading_size": "title-sm",
            "heading_tag": "h2",
            "highlighted_text": "none",
            "highlighted_scribble": "circle"
          }
        },
        "liquid_8e3Q6t": {
          "type": "liquid",
          "settings": {
            "liquid": "<p style=\"\n    font-weight: 500;\n    font-size: 22px;\n    margin-bottom: 0px;\n\">痛みレスな快適ムダ毛ケアを！<\/p>"
          }
        }
      },
      "block_order": [
        "heading_TLEnRH",
        "liquid_8e3Q6t"
      ],
      "settings": {
        "text_alignment": "center",
        "text_alignment_mobile": "center",
        "heading": "",
        "heading_size": "title-md",
        "heading_alignment": "text-left md:items-end md:flex-row",
        "heading_tag": "h2",
        "subheading": "",
        "description": "",
        "button_label": "",
        "button_link": "",
        "highlighted_text": "none",
        "highlighted_scribble": "circle",
        "color_text": "",
        "color_background": "#fae6ea",
        "gradient_background": "",
        "color_highlight": "",
        "gradient_highlight": "",
        "color_button_text": "",
        "color_button_background": "",
        "color_button_gradient": "",
        "padding_top": 60,
        "padding_bottom": 0,
        "divider": false,
        "narrow": true,
        "rounded": false
      }
    },
    "slideshow_A7UNhp": {
      "type": "slideshow",
      "blocks": {
        "image_dcUk9a": {
          "type": "image",
          "settings": {
            "image": "shopify:\/\/shop_images\/B0001B4.webp",
            "image_mobile": "shopify:\/\/shop_images\/B0001B4_MB.jpg",
            "heading": "",
            "heading_size": "title-lg tracking-heading",
            "heading_tag": "h2",
            "button_label": "",
            "button_link": "",
            "button_secondary_style": false
          }
        },
        "image_Kip8C6": {
          "type": "image",
          "settings": {
            "image": "shopify:\/\/shop_images\/49ae66c95b29ecf5ee2b35e61b0b876e_0168dbcf-144a-470e-90de-3d37a6156f39.png",
            "image_mobile": "shopify:\/\/shop_images\/3_63814f60-6859-426c-bc4b-47cf22582f68.png",
            "heading": "",
            "heading_size": "title-sm",
            "heading_tag": "h2",
            "button_label": "",
            "button_link": "",
            "button_secondary_style": false
          }
        },
        "image_KA4jFK": {
          "type": "image",
          "settings": {
            "image": "shopify:\/\/shop_images\/b0b90a30f0f0b38a3da6b9be6283422c_40d767ec-6442-4140-aa8f-65e006f23c12.png",
            "image_mobile": "shopify:\/\/shop_images\/2_67f93221-ba32-46dc-9f44-a63014553f2b.png",
            "heading": "",
            "heading_size": "title-sm",
            "heading_tag": "h2",
            "button_label": "",
            "button_link": "",
            "button_secondary_style": false
          }
        },
        "image_nMpaC7": {
          "type": "image",
          "disabled": true,
          "settings": {
            "image": "shopify:\/\/shop_images\/1-4_3dca9691-a354-40f9-8543-69b92acd0f0b.png",
            "image_mobile": "shopify:\/\/shop_images\/1_afcbfd30-c1fd-4d53-b01e-98c4cc6cc06d.png",
            "heading": "",
            "heading_size": "title-sm",
            "heading_tag": "h2",
            "button_label": "",
            "button_link": "",
            "button_secondary_style": false
          }
        }
      },
      "block_order": [
        "image_dcUk9a",
        "image_Kip8C6",
        "image_KA4jFK",
        "image_nMpaC7"
      ],
      "settings": {
        "autoplay": true,
        "autoplay_speed": 3,
        "show_navigation": true,
        "image_height": "600px",
        "content_width": "small",
        "image_height_mobile": "adapt",
        "color_text": "#171717",
        "color_background": "#fae6ea",
        "gradient_background": "",
        "color_button_text": "#171717",
        "color_button_background": "#ffffff",
        "color_button_gradient": "",
        "color_overlay": "rgba(0,0,0,0)",
        "padding_top": 40,
        "padding_bottom": 40,
        "divider": false,
        "full_width": true,
        "rounded": false,
        "enable_parallax": false,
        "parallax_direction": "vertical"
      }
    },
    "rich_text_fNhLAi": {
      "type": "rich-text",
      "blocks": {
        "text_AijDXM": {
          "type": "text",
          "settings": {
            "text": "<p>*ユーロモニターインターナショナル調べ；2022年世界の家庭用光美容器の小売販売台数から測定；2023年12月に実施された調査に基づく；家庭用光美容器とは、IPLやレーザーといった光エネルギーを利用して無駄毛を処理する家庭用機器を指す。<\/p>",
            "text_size": "subtext-custom",
            "text_max_size": 12,
            "text_font": "body",
            "secondary_color": true,
            "highlighted_text": "none",
            "highlighted_scribble": "circle"
          }
        }
      },
      "block_order": [
        "text_AijDXM"
      ],
      "settings": {
        "text_alignment": "left",
        "text_alignment_mobile": "left",
        "heading": "",
        "heading_size": "title-md",
        "heading_alignment": "text-left md:items-end md:flex-row",
        "heading_tag": "h2",
        "subheading": "",
        "description": "",
        "button_label": "",
        "button_link": "",
        "highlighted_text": "none",
        "highlighted_scribble": "circle",
        "color_text": "",
        "color_background": "#fae6ea",
        "gradient_background": "",
        "color_highlight": "",
        "gradient_highlight": "",
        "color_button_text": "",
        "color_button_background": "",
        "color_button_gradient": "",
        "padding_top": 0,
        "padding_bottom": 28,
        "divider": false,
        "narrow": true,
        "rounded": false
      }
    },
    "image_with_text_overlay_QwcYgJ": {
      "type": "image-with-text-overlay",
      "blocks": {
        "heading_ftfPCi": {
          "type": "heading",
          "settings": {
            "heading": "SNS Giveaway",
            "heading_size": "title-sm",
            "heading_tag": "h2",
            "highlighted_text": "none",
            "highlighted_scribble": "circle"
          }
        }
      },
      "block_order": [
        "heading_ftfPCi"
      ],
      "disabled": true,
      "settings": {
        "transparent_header": false,
        "image_height": "adapt",
        "content_width": "small",
        "content_position": "md:items-end md:justify-start",
        "text_alignment": "left",
        "image_height_mobile": "auto",
        "content_position_mobile": "items-end justify-start",
        "text_alignment_mobile": "left",
        "color_text": "#171717",
        "color_highlight": "#e0a580",
        "gradient_highlight": "",
        "color_button_text": "#171717",
        "color_button_background": "#ffffff",
        "color_button_gradient": "",
        "color_overlay": "rgba(0,0,0,0)",
        "overlay_opacity": 70,
        "padding_top": 0,
        "padding_bottom": 0,
        "divider": false,
        "full_width": true,
        "rounded": false,
        "enable_parallax": false,
        "parallax_direction": "vertical"
      }
    },
    "scrolling_text_jnc3Jg": {
      "type": "scrolling-text",
      "blocks": {
        "image_Lim4tw": {
          "type": "image",
          "settings": {
            "height": 80
          }
        },
        "image_ELCEHw": {
          "type": "image",
          "settings": {
            "height": 80
          }
        },
        "image_4hLViK": {
          "type": "image",
          "settings": {
            "height": 80
          }
        },
        "image_rRcc6y": {
          "type": "image",
          "settings": {
            "height": 80
          }
        },
        "image_rNynGA": {
          "type": "image",
          "settings": {
            "height": 80
          }
        }
      },
      "block_order": [
        "image_Lim4tw",
        "image_ELCEHw",
        "image_4hLViK",
        "image_rRcc6y",
        "image_rNynGA"
      ],
      "disabled": true,
      "settings": {
        "direction": "left",
        "speed": 1.6,
        "grid_horizontal": 70,
        "enable_twin": false,
        "enable_parallax": true,
        "color_text": "",
        "color_background": "",
        "gradient_background": "",
        "padding_top": 36,
        "padding_bottom": 36,
        "divider": false,
        "rounded": false
      }
    }
  },
  "order": [
    "main-page",
    "countdown_timer_7hMhKU",
    "air10_banner_k6tjDe",
    "rich_text_9QNjGY",
    "rich_text_KqEygY",
    "images_with_text_VM9xpj",
    "image_with_text_mRRfzk",
    "image_with_text_ew8B4b",
    "image_with_text_DnWprU",
    "image_with_text_Tn8xy6",
    "preheat_slide_diy_BbbmNt",
    "featured_collection_FMUB6U",
    "image_with_text_NpDc6j",
    "rich_text_Yp4nKi",
    "image_with_text_overlay_ACKQTF",
    "rich_text_Kp8ert",
    "video_XX9qmL",
    "rich_text_ixrKrJ",
    "slideshow_A7UNhp",
    "rich_text_fNhLAi",
    "image_with_text_overlay_QwcYgJ",
    "scrolling_text_jnc3Jg"
  ]
}
