{
  "sections": {
    "main": {
      "type": "main-page",
      "disabled": true,
      "settings": {
        "heading_size": "title-xl tracking-heading",
        "heading_tag": "h1",
        "text_size": "text-base",
        "padding_top": 72,
        "padding_bottom": 100,
        "divider": false,
        "narrow": true,
        "rounded": false
      }
    },
    "css_module_cqi7Wp": {
      "type": "css-module",
      "settings": {
        "html_cont": "<link rel=\"stylesheet\" href=\"\/\/www.ulike.com\/cdn\/shop\/t\/116\/assets\/swiper-bundle.min.css\">\n<script src=\"\/\/www.ulike.com\/cdn\/shop\/t\/116\/assets\/swiper-bundle.min.aio.min.js\"><\/script>\n<style>\n.mini-cont .container {\n  max-width: 1396px;\n}\n<\/style>"
      }
    },
    "technology_tab_6JqfEm": {
      "type": "technology-tab",
      "blocks": {
        "item_efKiiH": {
          "type": "item",
          "settings": {
            "is_check": false,
            "text": "サファイア冷感技術",
            "link": "https:\/\/jp.ulike.com\/pages\/technology-ice-cooling"
          }
        },
        "item_rMgGA3": {
          "type": "item",
          "settings": {
            "is_check": false,
            "text": "ダブルランプ技術",
            "link": "https:\/\/jp.ulike.com\/pages\/technology-dual-lights"
          }
        },
        "item_MGty4C": {
          "type": "item",
          "settings": {
            "is_check": true,
            "text": "スキンセンサー技術",
            "link": "https:\/\/jp.ulike.com\/pages\/technology-skinsensor"
          }
        }
      },
      "block_order": [
        "item_efKiiH",
        "item_rMgGA3",
        "item_MGty4C"
      ],
      "settings": {}
    },
    "custom_banner_XzGPMV": {
      "type": "custom__banner",
      "name": "Custom Banner",
      "settings": {
        "full_width": true,
        "image": "shopify:\/\/shop_images\/Technology_Page-Dual_Lights_Banner__1920x495_40883a59-2193-43e3-8084-5cb1e9f48f37.png",
        "image_mobile": "shopify:\/\/shop_images\/M-Technology_Page-Sapphire_Ice_Cooling_Banner__375x540_d3e6f6c7-bb18-489d-a246-53a9437b7b53.png",
        "tle": "<p>スキンセンサー技術<\/p>",
        "tle_size": 50,
        "mobile_tle_size": 30,
        "sub_tle": "<p>やけどや刺激を防ぎ、ほとんどの肌タイプ*に対してより安全な自宅でのムダ毛ケアを実現する、Ulikeの肌に優しい技術をご紹介。リアルタイムでエネルギーレベルをカスタマイズします。*肌質により個人差があります。使用前に取扱説明書をよくお読みください。<\/p>",
        "sub_tle_left": 0,
        "mobile_sub_tle_left": 0,
        "content_bottom": 0,
        "mobile_content_bottom": 0,
        "sub_tle1": "",
        "note_full_width": true,
        "note": "",
        "button_txt": "",
        "link_url": "",
        "text_position": "middle_left",
        "mobile_text_position": "top_center",
        "text_color": "#000000",
        "background": "rgba(0,0,0,0)"
      }
    },
    "technology_title_yfakHP": {
      "type": "technology-title",
      "settings": {
        "title": "従来のIPLが肌を傷つける理由と、Ulikeの肌想いIPL技術",
        "bg_color": "#fff"
      }
    },
    "technology_pain_XaxjQE": {
      "type": "technology-pain",
      "settings": {
        "title": "問題：自動パワー調整機能のないデバイスは肌ダメージを引き起こす可能性があります。",
        "text": "<ul><li><strong>安全性と効果の限界:  <\/strong>スマートなパワー調整機能がないため、従来のIPLデバイスは必要以上のエネルギーを照射し、特に色の濃い肌色の方にやけどや不快感を引き起こす可能性があります。逆に、エネルギーが不足すると、敏感肌の自宅でのムダ毛ケアが効果的でなくなります。<\/li><li><strong>使用の不便さ：<\/strong> 従来のIPLデバイスは、肌色やトリートメント部位に基づいて手動でパワーを調整する必要があります。このプロセスは推測に頼ることになり、間違った選択する可能性を高め、時間もかかります。<\/li><\/ul>"
      }
    },
    "technology_skin_GDFPME": {
      "type": "technology-skin",
      "blocks": {
        "item_4Xc7m3": {
          "type": "item",
          "settings": {
            "image": "shopify:\/\/shop_images\/PC_SHR_434a99fd-9b4c-45b7-98e9-083e1ecabe32.jpg",
            "text": "やけどや刺激なし*",
            "text1": "スキンセンサーは色の濃い肌色を検出した際にパワーレベルを調整し、自然に色の濃い部位での過度な熱蓄積を防ぎ、安全な自宅でのIPLムダ毛ケアを実現します。<br>*刺激の感じ方には個人差と部位差があります。"
          }
        },
        "item_VjmTQe": {
          "type": "item",
          "settings": {
            "image": "shopify:\/\/shop_images\/PC_SHR_434a99fd-9b4c-45b7-98e9-083e1ecabe32.jpg",
            "text": "毎回最適な設定",
            "text1": "肌色に合わせて自動的にエネルギー出力を調整し、推測に頼ることなく最も安全な自宅でのムダ毛ケアトリートメントを提供します。"
          }
        },
        "item_a6mFeq": {
          "type": "item",
          "settings": {
            "image": "shopify:\/\/shop_images\/PC_SHR_434a99fd-9b4c-45b7-98e9-083e1ecabe32.jpg",
            "text": "スマートで手間いらずなケア",
            "text1": "スキンセンサーにより、手動調整は一切不要——自動的で最適にパワーを調整し、自宅での色の濃い肌にも簡単で安全なムダ毛ケアを実現します*。<br>*肌色による効果や安全性には個人差があります。"
          }
        }
      },
      "block_order": [
        "item_4Xc7m3",
        "item_VjmTQe",
        "item_a6mFeq"
      ],
      "settings": {
        "diy_class": "border-skin",
        "text": "Ulikeの違い：より賢く、より安全なムダ毛ケアを実現するスキンセンサー技術",
        "text1": ""
      }
    },
    "technology_title_hzndhQ": {
      "type": "technology-title",
      "settings": {
        "title": "スキンセンサーの仕組み",
        "bg_color": "#fff"
      }
    },
    "technology_image_text_Fai4a3": {
      "type": "technology-image-text",
      "blocks": {
        "item_YnwPmR": {
          "type": "item",
          "settings": {
            "check_box": false,
            "image": "shopify:\/\/shop_images\/PC_SHR_434a99fd-9b4c-45b7-98e9-083e1ecabe32.jpg",
            "text": "",
            "text1": "<p>スキンセンサーは、光美容器の照射面を動かすたびに肌を継続的にスキャンし、リアルタイムで色素の濃さを検出します。<\/p><p>肌ダメージのないムダ毛ケア<em>を念頭に置いて、各部位の肌色に基づいて自動的にパワー出力を微調整し、すべての肌色<\/em>に対して安全で効果的なムダ毛ケアのための最適なエネルギーレベルを確保します。これにより、不快感を引き起こす可能性のある過度なパワーを防ぎながら、結果を低下させる可能性のあるエネルギー不足を回避し、敏感肌の自宅でのIPLムダ毛ケアに完璧にバランスの取れたトリートメントを提供します*。<\/p><p>*効果や刺激の感じ方には個人差と部位差があります。<br\/><br\/><\/p>"
          }
        }
      },
      "block_order": [
        "item_YnwPmR"
      ],
      "custom_css": [
        ".technology-image-text {padding-bottom: 50px;}"
      ],
      "settings": {
        "text": ""
      }
    },
    "technology_title_hMhmge": {
      "type": "technology-title",
      "settings": {
        "title": "実証された結果、信頼されるレビュー",
        "bg_color": "#f6f6f6"
      }
    },
    "technology_trusted_zLEAHG": {
      "type": "technology-trusted",
      "blocks": {
        "item_YMGBPd": {
          "type": "item",
          "settings": {
            "image": "shopify:\/\/shop_images\/PC_SHR_434a99fd-9b4c-45b7-98e9-083e1ecabe32.jpg",
            "text": "**98%***のユーザーが、わずか数週間の使用でより滑らかで柔らかな肌を報告",
            "text1": "*国際認証機関による試験結果。効果には個人差及び部位差があります。"
          }
        },
        "item_gELfxf": {
          "type": "item",
          "settings": {
            "image": "shopify:\/\/shop_images\/PC_SHR_434a99fd-9b4c-45b7-98e9-083e1ecabe32.jpg",
            "text": "**100%***のユーザーが、敏感部位でも快適なムダ毛ケアを体験",
            "text1": "*国際認証機関による試験結果。効果には個人差及び部位差があります。"
          }
        },
        "item_UxVpXG": {
          "type": "item",
          "settings": {
            "image": "shopify:\/\/shop_images\/PC_SHR_434a99fd-9b4c-45b7-98e9-083e1ecabe32.jpg",
            "text": "**99%***のユーザーが、手動調整不要の手間いらずなトリートメントを実感",
            "text1": "*国際認証機関による試験結果。効果には個人差及び部位差があります。"
          }
        }
      },
      "block_order": [
        "item_YMGBPd",
        "item_gELfxf",
        "item_UxVpXG"
      ],
      "settings": {
        "text": "ユーザー報告による結果"
      }
    },
    "technology_media_TM48xc": {
      "type": "technology-media",
      "blocks": {
        "item_xBUzNc": {
          "type": "item",
          "settings": {
            "text": "\"The most comfortable at-home hair removal device\""
          }
        },
        "item_CWdxdG": {
          "type": "item",
          "settings": {
            "text": "\"This Ulike device has been a game changer!\""
          }
        },
        "item_h394aC": {
          "type": "item",
          "settings": {
            "text": "\"It's no wonder this popular product is flying off the shelves\""
          }
        }
      },
      "block_order": [
        "item_xBUzNc",
        "item_CWdxdG",
        "item_h394aC"
      ],
      "disabled": true,
      "settings": {
        "text": "As seen in the media."
      }
    },
    "technology_title_HnMfza": {
      "type": "technology-title",
      "settings": {
        "title": "おすすめ製品",
        "bg_color": "#fff"
      }
    },
    "product_area_box_new_qHMaja": {
      "type": "product-area-box-new",
      "blocks": {
        "item_txdWgM": {
          "type": "item",
          "settings": {
            "product": "air10-ipl-hair-removal",
            "tag": "",
            "image": "shopify:\/\/shop_images\/A10.png",
            "color": "ホワイトゴールド",
            "color1": "",
            "color2": "",
            "title": "Ulike Air10 IPL光美容器",
            "content": "<p><strong>Ulikeシリーズの人気モデルUlike Air 10。進化した痛みレス技術でサロン級ケアを。<\/strong><\/p>",
            "btn_txt": "<p>詳しくはこちら&gt;&gt;<\/p>",
            "link": "https:\/\/jp.ulike.com\/products\/air10-ipl-hair-removal",
            "msg_txt": "",
            "pj_txt": "<p>4.6\/5 (<strong>2422<\/strong>)<\/p>",
            "pj_txt_bt": "レビューを見る",
            "review1": 73,
            "review2": 16,
            "review3": 10,
            "review4": 0,
            "review5": 1,
            "pj_txt_lj": "すべてのレビューを見る",
            "link1": "https:\/\/jp.ulike.com\/products\/air10-ipl-hair-removal"
          }
        },
        "item_yRkfFP": {
          "type": "item",
          "settings": {
            "product": "airpro-s_hair_removal",
            "tag": "",
            "image": "shopify:\/\/shop_images\/ProS_c530c94a-1b49-4272-a14c-5bff7fd25db5.png",
            "color": "バイオレット",
            "color1": "",
            "color2": "",
            "title": "Ulike AirPro S IPL光美容器",
            "content": "<p><strong>コンパクトモデルUlike Air Proがさらにアップグレード。最大22J*で、効果実感まで2週間。<\/strong><\/p>",
            "btn_txt": "<p>詳しくはこちら&gt;&gt;<\/p>",
            "link": "https:\/\/jp.ulike.com\/products\/airpro-s_hair_removal",
            "msg_txt": "",
            "pj_txt": "<p>4.9\/5 (<strong>39<\/strong>)<\/p>",
            "pj_txt_bt": "レビュー",
            "review1": 92,
            "review2": 6,
            "review3": 2,
            "review4": 0,
            "review5": 0,
            "pj_txt_lj": "すべてのレビューを見る",
            "link1": "https:\/\/jp.ulike.com\/products\/airpro-s_hair_removal"
          }
        }
      },
      "block_order": [
        "item_txdWgM",
        "item_yRkfFP"
      ],
      "settings": {
        "background": "rgba(0,0,0,0)"
      }
    }
  },
  "order": [
    "main",
    "css_module_cqi7Wp",
    "technology_tab_6JqfEm",
    "custom_banner_XzGPMV",
    "technology_title_yfakHP",
    "technology_pain_XaxjQE",
    "technology_skin_GDFPME",
    "technology_title_hzndhQ",
    "technology_image_text_Fai4a3",
    "technology_title_hMhmge",
    "technology_trusted_zLEAHG",
    "technology_media_TM48xc",
    "technology_title_HnMfza",
    "product_area_box_new_qHMaja"
  ]
}
