{
  "sections": {
    "main-page": {
      "type": "main-page",
      "disabled": true,
      "settings": {
        "heading_size": "title-xl tracking-heading",
        "heading_tag": "h1",
        "text_size": "text-base",
        "padding_top": 72,
        "padding_bottom": 120,
        "divider": false,
        "narrow": true,
        "rounded": false
      }
    },
    "image_with_text_overlay_4RREgH": {
      "type": "image-with-text-overlay",
      "settings": {
        "transparent_header": true,
        "image_height": "adapt",
        "content_width": "small",
        "content_position": "md:items-end md:justify-start",
        "text_alignment": "left",
        "image_height_mobile": "adapt",
        "content_position_mobile": "items-end justify-start",
        "text_alignment_mobile": "left",
        "color_text": "#ffffff",
        "color_highlight": "#e0a580",
        "gradient_highlight": "",
        "color_button_text": "#171717",
        "color_button_background": "#ffffff",
        "color_button_gradient": "",
        "color_overlay": "#171717",
        "overlay_opacity": 70,
        "padding_top": 0,
        "padding_bottom": 0,
        "divider": false,
        "full_width": true,
        "rounded": false,
        "enable_parallax": true,
        "parallax_direction": "vertical"
      }
    },
    "multicolumn_P4jfta": {
      "type": "multicolumn",
      "blocks": {
        "column_c3L7P6": {
          "type": "column",
          "settings": {
            "show_border": false,
            "text_alignment": "center",
            "text_alignment_mobile": "center",
            "image": "shopify:\/\/shop_images\/0205_be1fa01a-c9b0-400c-8f1c-c27302568124.jpg",
            "image_ratio": "adapt",
            "heading": "Topic title",
            "heading_size": "text-base-xl",
            "text": "",
            "button_label": "",
            "button_link": "",
            "highlighted_text": "none",
            "highlighted_scribble": "circle"
          }
        },
        "column_9xPTbP": {
          "type": "column",
          "settings": {
            "show_border": false,
            "text_alignment": "center",
            "text_alignment_mobile": "center",
            "image": "shopify:\/\/shop_images\/0205_be1fa01a-c9b0-400c-8f1c-c27302568124.jpg",
            "image_ratio": "adapt",
            "heading": "Topic title",
            "heading_size": "text-base-xl",
            "text": "",
            "button_label": "",
            "button_link": "",
            "highlighted_text": "none",
            "highlighted_scribble": "circle"
          }
        },
        "column_kHrU9W": {
          "type": "column",
          "settings": {
            "show_border": false,
            "text_alignment": "center",
            "text_alignment_mobile": "center",
            "image": "shopify:\/\/shop_images\/0205_be1fa01a-c9b0-400c-8f1c-c27302568124.jpg",
            "image_ratio": "adapt",
            "heading": "Topic title",
            "heading_size": "text-base-xl",
            "text": "",
            "button_label": "",
            "button_link": "",
            "highlighted_text": "none",
            "highlighted_scribble": "circle"
          }
        }
      },
      "block_order": [
        "column_c3L7P6",
        "column_9xPTbP",
        "column_kHrU9W"
      ],
      "settings": {
        "columns": 3,
        "columns_mobile": "1",
        "swipe_on_mobile": true,
        "heading": "Support Topic",
        "heading_size": "title-sm",
        "heading_alignment": "text-center md:items-center",
        "heading_tag": "h2",
        "subheading": "",
        "description": "",
        "button_label": "",
        "button_link": "",
        "highlighted_text": "none",
        "highlighted_scribble": "circle",
        "color_text": "",
        "color_background": "",
        "gradient_background": "",
        "color_highlight": "",
        "gradient_highlight": "",
        "color_button_text": "",
        "color_button_background": "",
        "color_button_gradient": "",
        "padding_top": 72,
        "padding_bottom": 72,
        "divider": false,
        "full_width": false,
        "rounded": false
      }
    },
    "contact_form_9LycXN": {
      "type": "contact-form",
      "settings": {
        "heading": "Contact Us",
        "heading_size": "title-sm",
        "heading_alignment": "text-left md:items-end md:flex-row",
        "heading_tag": "h2",
        "subheading": "",
        "description": "",
        "button_label": "",
        "button_link": "",
        "highlighted_text": "none",
        "highlighted_scribble": "circle",
        "color_text": "",
        "color_background": "",
        "gradient_background": "",
        "color_highlight": "",
        "gradient_highlight": "",
        "color_button_text": "",
        "color_button_background": "",
        "color_button_gradient": "",
        "padding_top": 72,
        "padding_bottom": 72,
        "divider": false,
        "narrow": true,
        "rounded": false
      }
    }
  },
  "order": [
    "main-page",
    "image_with_text_overlay_4RREgH",
    "multicolumn_P4jfta",
    "contact_form_9LycXN"
  ]
}
